mongots/__init__.py
mongots/aggregateby.py
mongots/client.py
mongots/collection.py
mongots/constants.py
mongots/database.py
mongots/dataframe.py
mongots/insert.py
mongots/metadata.py
mongots/query.py
mongots/types.py
mongots/utils.py
mongots-0.2.0.dist-info/DESCRIPTION.rst
mongots-0.2.0.dist-info/METADATA
mongots-0.2.0.dist-info/RECORD
mongots-0.2.0.dist-info/WHEEL
mongots-0.2.0.dist-info/metadata.json
mongots-0.2.0.dist-info/top_level.txt
