Metadata-Version: 2.0
Name: mongots
Version: 0.2.0
Summary: A fast API for storing and querying time series in MongoDb
Home-page: https://github.com/AntoineToubhans/MongoTs
Author: Antoine Toubhans
Author-email: antoine@toubhans.org
License: MIT
Keywords: mongo,pymongo,timeserie
Platform: UNKNOWN
Classifier: Development Status :: 2 - Pre-Alpha
Classifier: Intended Audience :: Developers
Classifier: License :: OSI Approved :: MIT License
Classifier: Natural Language :: English
Classifier: Programming Language :: Python :: 3.3
Classifier: Programming Language :: Python :: 3.4
Classifier: Programming Language :: Python :: 3.5
Classifier: Programming Language :: Python :: 3.6
Requires-Dist: pandas
Requires-Dist: parse
Requires-Dist: pymongo
